scribepy/__init__.py
scribepy/scribepy.py
scribepy/utils.py
ScribePy-0.1.2.dist-info/LICENSE
ScribePy-0.1.2.dist-info/METADATA
ScribePy-0.1.2.dist-info/WHEEL
ScribePy-0.1.2.dist-info/top_level.txt
ScribePy-0.1.2.dist-info/RECORD
