Metadata-Version: 2.1
Name: ScribePy
Version: 0.1.2
Summary: Python library for generating documentation
Home-page: https://github.com/hipnologo/ScribePy
Author: Fabio Carvalho
Author-email: Fabio Carvalho <hipnologo@gmail.com>
License: Apache License
Project-URL: Homepage, https://github.com/hipnologo/ScribePy
Project-URL: Bug Tracker, https://github.com/hipnologo/ScribePy/issues
Keywords: documentation,python
Classifier: Development Status :: 4 - Beta
Classifier: Intended Audience :: Developers
Classifier: License :: OSI Approved :: Apache Software License
Classifier: Programming Language :: Python :: 3
Classifier: Programming Language :: Python :: 3.6
Classifier: Programming Language :: Python :: 3.7
Classifier: Programming Language :: Python :: 3.8
Classifier: Programming Language :: Python :: 3.9
License-File: LICENSE
Requires-Dist: markdown (>=3.3.3)
Requires-Dist: Pygments (>=2.7.4)
